jki_python_bridge_for_labview/__init__.py
jki_python_bridge_for_labview/labview.py
jki_python_bridge_for_labview-5.0.1.dist-info/METADATA
jki_python_bridge_for_labview-5.0.1.dist-info/WHEEL
jki_python_bridge_for_labview-5.0.1.dist-info/licenses/LICENSE
jki_python_bridge_for_labview-5.0.1.dist-info/RECORD
