Metadata-Version: 2.1
Name: jki-python-bridge-for-labview
Version: 5.0.1
Summary: JKI Python Bridge for LabVIEW. Easily control your LabVIEW applications from python via define custom APIs.
Author-email: JKI <info@jki.net>
License-Expression: BSD-2-Clause-Patent
License-File: LICENSE
Provides-Extra: dev
